moovs/__init__.py
moovs_business/__init__.py
moovs_business/constants.py
moovs_business/structs.py
moovs_business/flows/__init__.py
moovs_business/flows/detection.py
moovs_business/flows/human_pose.py
moovs_business/flows/tracking.py
moovs_business/flows/subs/__init__.py
moovs_business/flows/subs/descriptor.py
moovs_business/flows/subs/tracks.py
moovs_business/tracking/__init__.py
moovs_business/tracking/iou_matching.py
moovs_business/tracking/kalman_filter.py
moovs_business/tracking/linear_assignment.py
moovs_business/tracking/moving_average.py
moovs_business/utils/__init__.py
moovs_business/utils/helpers.py
moovs_business/utils/math.py
moovs_business/utils/pose.py
moovs_business/utils/resize.py
moovs_business/utils/serialize.py
moovs_business/utils/tracks.py
moovs_business-0.0.2.dist-info/METADATA
moovs_business-0.0.2.dist-info/WHEEL
moovs_business-0.0.2.dist-info/top_level.txt
moovs_business-0.0.2.dist-info/RECORD
