Metadata-Version: 2.1
Name: moovs-business
Version: 0.0.2
Summary: Empower your software with advanced object detection, human pose estimation, and real-time multi-object tracking to revolutionize how you interact with the physical world.
Home-page: https://github.com/dotmoovs/moovs-business
Author: Guilherme Viveiros, Rui Reis.
Author-email: guilherme.viveiros@dotmoovs.com, rui.reis@dotmoovs.com
Requires-Python: >=3.7
Requires-Dist: numpy ==1.24.4
Requires-Dist: vidgear ==0.3.2
Requires-Dist: pyqflow ==1.1.1
Requires-Dist: torch
Requires-Dist: torchvision
Requires-Dist: pydantic
Requires-Dist: scipy
